jsonator/__init__.py
jsonator/__main__.py
jsonator/enum.py
jsonator/jsonator.py
jsonator/models.py
jsonator/output.py
jsonator/report.py
jsonator-0.1.11.dist-info/METADATA
jsonator-0.1.11.dist-info/WHEEL
jsonator-0.1.11.dist-info/entry_points.txt
jsonator-0.1.11.dist-info/licenses/LICENSE
jsonator-0.1.11.dist-info/RECORD
