Metadata-Version: 2.1
Name: jsonator
Version: 0.1.11
Summary: JSON formatting and validating tool
Project-URL: Homepage, https://github.com/sfominx/jsonator
Author-email: Sergey Fomin <sergiusnn@gmail.com>
License-File: LICENSE
Classifier: License :: OSI Approved :: BSD License
Classifier: Programming Language :: Python :: 3
Requires-Python: >=3.8
